preprocessing/__init__.py
preprocessing/errors.py
preprocessing/spellcheck.py
preprocessing/text.py
preprocessing/data/corpora/stopwords/english
preprocessing/data/tokenizers/punkt/english.pickle
preprocessing/data/tokenizers/punkt/PY3/english.pickle
preprocessing-0.1.13.data/scripts/demo
preprocessing-0.1.13.dist-info/DESCRIPTION.rst
preprocessing-0.1.13.dist-info/METADATA
preprocessing-0.1.13.dist-info/RECORD
preprocessing-0.1.13.dist-info/WHEEL
preprocessing-0.1.13.dist-info/metadata.json
preprocessing-0.1.13.dist-info/top_level.txt
tests/__init__.py
tests/test_spellcheck.py
tests/test_text.py
