Metadata-Version: 1.2
Name: preprocessing
Version: 0.1.13
Summary: pre-processing package for text strings
Home-page: https://github.com/SpotlightData/preprocessing
Author: Mitchell Murphy
Author-email: mwtmurphy@gmail.com
License: MIT
Keywords: text pre-processing
Platform: UNKNOWN
Classifier: Natural Language :: English
Classifier: Programming Language :: Python :: 3
Classifier: Programming Language :: Python :: 3.6
Requires-Python: >=3
